depscan/__init__.py
depscan/models.py
depscan/package_mapping.py
depscan-0.1.5.dist-info/METADATA
depscan-0.1.5.dist-info/WHEEL
depscan-0.1.5.dist-info/entry_points.txt
depscan-0.1.5.dist-info/licenses/LICENSE
depscan-0.1.5.dist-info/RECORD
