Metadata-Version: 2.4
Name: depscan
Version: 0.1.5
Summary: A fast Python dependency analyzer that automatically discovers and extracts third-party imports
Project-URL: Homepage, https://github.com/linkedlist771/depscan
Project-URL: Repository, https://github.com/linkedlist771/depscan.git
Author-email: linkedlist771 <213193509seu@gmail.com>
License: MIT
License-File: LICENSE
Keywords: analyzer,dependency,imports,requirements
Classifier: Development Status :: 4 - Beta
Classifier: Intended Audience :: Developers
Classifier: License :: OSI Approved :: MIT License
Classifier: Programming Language :: Python :: 3
Classifier: Programming Language :: Python :: 3.7
Classifier: Programming Language :: Python :: 3.8
Classifier: Programming Language :: Python :: 3.9
Classifier: Programming Language :: Python :: 3.10
Classifier: Programming Language :: Python :: 3.11
Classifier: Programming Language :: Python :: 3.12
Classifier: Topic :: Software Development :: Libraries :: Python Modules
Requires-Python: >=3.7
Requires-Dist: typing
